DigiPathAI/.DS_Store
DigiPathAI/Segmentation.py
DigiPathAI/__init__.py
DigiPathAI/main_server.py
DigiPathAI/new_Segmentation.py
DigiPathAI/helpers/__init__.py
DigiPathAI/helpers/convert_to_pyramidal.py
DigiPathAI/helpers/utils.py
DigiPathAI/loaders/__init__.py
DigiPathAI/loaders/dataloader.py
DigiPathAI/loaders/inference_data_loader.py
DigiPathAI/models/__init__.py
DigiPathAI/models/deeplabv3.py
DigiPathAI/models/densenet.py
DigiPathAI/models/inception.py
DigiPathAI/static/css/.DS_Store
DigiPathAI/static/css/bootstrap-grid.css
DigiPathAI/static/css/bootstrap-grid.css.map
DigiPathAI/static/css/bootstrap-grid.min.css
DigiPathAI/static/css/bootstrap-grid.min.css.map
DigiPathAI/static/css/bootstrap-reboot.css
DigiPathAI/static/css/bootstrap-reboot.css.map
DigiPathAI/static/css/bootstrap-reboot.min.css
DigiPathAI/static/css/bootstrap-reboot.min.css.map
DigiPathAI/static/css/bootstrap.css
DigiPathAI/static/css/bootstrap.css.map
DigiPathAI/static/css/bootstrap.min.css
DigiPathAI/static/css/bootstrap.min.css.map
DigiPathAI/static/css/dark-mode.css
DigiPathAI/static/css/font-awesome.min.css
DigiPathAI/static/css/style.css
DigiPathAI/static/fonts/FontAwesome.otf
DigiPathAI/static/fonts/fontawesome-webfont.eot
DigiPathAI/static/fonts/fontawesome-webfont.svg
DigiPathAI/static/fonts/fontawesome-webfont.ttf
DigiPathAI/static/fonts/fontawesome-webfont.woff
DigiPathAI/static/fonts/fontawesome-webfont.woff2
DigiPathAI/static/images/.DS_Store
DigiPathAI/static/images/avinash.png
DigiPathAI/static/images/fullpage_grouphover.png
DigiPathAI/static/images/fullpage_hover.png
DigiPathAI/static/images/fullpage_pressed.png
DigiPathAI/static/images/fullpage_rest.png
DigiPathAI/static/images/ganapath.png
DigiPathAI/static/images/haran.jpeg
DigiPathAI/static/images/haran.png
DigiPathAI/static/images/home_grouphover.png
DigiPathAI/static/images/home_hover.png
DigiPathAI/static/images/home_pressed.png
DigiPathAI/static/images/home_rest.png
DigiPathAI/static/images/mahendra.jpeg
DigiPathAI-0.1.5.dist-info/LICENSE
DigiPathAI-0.1.5.dist-info/METADATA
DigiPathAI-0.1.5.dist-info/WHEEL
DigiPathAI-0.1.5.dist-info/entry_points.txt
DigiPathAI-0.1.5.dist-info/top_level.txt
DigiPathAI-0.1.5.dist-info/RECORD
