Metadata-Version: 2.1
Name: DigiPathAI
Version: 0.1.5
Summary: Deep Learning toolbox for WSI (digital histopatology) analysis
Home-page: https://github.com/haranrk/DigiPathAI
Author: Avinash Kori, Haran Rajkumar
Author-email: koriavinash1@gmail.com, haranrajkumar97@gmail.com
License: UNKNOWN
Platform: UNKNOWN
Classifier: Programming Language :: Python :: 3.5
Classifier: License :: OSI Approved :: MIT License
Classifier: Operating System :: OS Independent
Requires-Dist: flask
Requires-Dist: openslide-python
Provides-Extra: gpu
Requires-Dist: torch ; extra == 'gpu'
Requires-Dist: torchvision ; extra == 'gpu'
Requires-Dist: opencv-python ; extra == 'gpu'
Requires-Dist: imgaug ; extra == 'gpu'
Requires-Dist: tqdm ; extra == 'gpu'
Requires-Dist: matplotlib ; extra == 'gpu'
Requires-Dist: scikit-learn ; extra == 'gpu'
Requires-Dist: scikit-image ; extra == 'gpu'
Requires-Dist: tensorflow-gpu (<2,>=1.14) ; extra == 'gpu'
Requires-Dist: pydensecrf ; extra == 'gpu'
Requires-Dist: tifffile ; extra == 'gpu'
Requires-Dist: pandas ; extra == 'gpu'
Requires-Dist: wget ; extra == 'gpu'
